llama_index/postprocessor/rankllm_rerank/__init__.py
llama_index/postprocessor/rankllm_rerank/base.py
llama_index_postprocessor_rankllm_rerank-0.6.1.dist-info/METADATA
llama_index_postprocessor_rankllm_rerank-0.6.1.dist-info/WHEEL
llama_index_postprocessor_rankllm_rerank-0.6.1.dist-info/licenses/LICENSE
llama_index_postprocessor_rankllm_rerank-0.6.1.dist-info/RECORD
