Metadata-Version: 2.4
Name: llama-index-postprocessor-rankllm-rerank
Version: 0.6.1
Summary: llama-index postprocessor rankllm-rerank integration
Author-email: Ryan Nguyen <ryan.nguyen@uwaterloo.ca>
License-Expression: MIT
License-File: LICENSE
Requires-Python: <4.0,>=3.10
Requires-Dist: llama-index-core<0.15,>=0.13.0
Requires-Dist: rank-llm>=0.21.0
